README.md
setup.py
EGene.egg-info/PKG-INFO
EGene.egg-info/SOURCES.txt
EGene.egg-info/dependency_links.txt
EGene.egg-info/requires.txt
EGene.egg-info/top_level.txt
egene/__init__.py
egene/benchmarker.py
egene/egene_main.py
egene/pygameTools.py
egene/test.py
egene/images/Icon.png