Metadata-Version: 2.1
Name: EGene
Version: 0.2.6
Summary: Tool for applying, visualizing, and training neural networks using a genetic algorithm
Home-page: https://github.com/Elan456/EGene
Author: Ethan Anderson
Author-email: telan4892@gmail.com
License: MIT
Platform: UNKNOWN
